odoo/addons/l10n_de_tax_statement_zm/README.rst
odoo/addons/l10n_de_tax_statement_zm/__init__.py
odoo/addons/l10n_de_tax_statement_zm/__manifest__.py
odoo/addons/l10n_de_tax_statement_zm/i18n/de.po
odoo/addons/l10n_de_tax_statement_zm/i18n/l10n_de_tax_statement_zm.pot
odoo/addons/l10n_de_tax_statement_zm/models/__init__.py
odoo/addons/l10n_de_tax_statement_zm/models/l10n_de_tax_statement.py
odoo/addons/l10n_de_tax_statement_zm/models/l10n_de_tax_statement_zm_line.py
odoo/addons/l10n_de_tax_statement_zm/readme/CONFIGURE.rst
odoo/addons/l10n_de_tax_statement_zm/readme/CONTRIBUTORS.rst
odoo/addons/l10n_de_tax_statement_zm/readme/DESCRIPTION.rst
odoo/addons/l10n_de_tax_statement_zm/readme/INSTALL.rst
odoo/addons/l10n_de_tax_statement_zm/readme/ROADMAP.rst
odoo/addons/l10n_de_tax_statement_zm/readme/USAGE.rst
odoo/addons/l10n_de_tax_statement_zm/report/report_tax_statement.xml
odoo/addons/l10n_de_tax_statement_zm/security/ir.model.access.csv
odoo/addons/l10n_de_tax_statement_zm/static/description/icon.png
odoo/addons/l10n_de_tax_statement_zm/static/description/index.html
odoo/addons/l10n_de_tax_statement_zm/tests/__init__.py
odoo/addons/l10n_de_tax_statement_zm/tests/test_l10n_de_tax_statement_zm.py
odoo/addons/l10n_de_tax_statement_zm/views/l10n_de_vat_statement_view.xml
odoo/addons/l10n_de_tax_statement_zm/views/report_tax_statement.xml
odoo12_addon_l10n_de_tax_statement_zm-12.0.1.0.0.99.dev4.dist-info/METADATA
odoo12_addon_l10n_de_tax_statement_zm-12.0.1.0.0.99.dev4.dist-info/WHEEL
odoo12_addon_l10n_de_tax_statement_zm-12.0.1.0.0.99.dev4.dist-info/top_level.txt
odoo12_addon_l10n_de_tax_statement_zm-12.0.1.0.0.99.dev4.dist-info/RECORD
